_psfmodels.cpython-311-darwin.so
psfmodels/_jax_bessel.py
psfmodels/_version.py
psfmodels/__init__.py
psfmodels/_core.py
psfmodels/_cuvec.py
psfmodels/_napari.py
psfmodels/py.typed
psfmodels/napari.yaml
_psfmodels-stubs/__init__.pyi
psfmodels-0.3.3.dist-info/RECORD
psfmodels-0.3.3.dist-info/LICENSE
psfmodels-0.3.3.dist-info/WHEEL
psfmodels-0.3.3.dist-info/entry_points.txt
psfmodels-0.3.3.dist-info/top_level.txt
psfmodels-0.3.3.dist-info/METADATA
