Metadata-Version: 2.1
Name: psfmodels
Version: 0.3.3
Summary: Scalar and vectorial models of the microscope point spread function (PSF).
Home-page: https://github.com/tlambert03/psfmodels
Author: Talley Lambert
Author-email: talley.lambert@gmail.com
License: GPL-3.0
Project-URL: Source Code, https://github.com/tlambert03/psfmodels
Classifier: Development Status :: 3 - Alpha
Classifier: Framework :: napari
Classifier: License :: OSI Approved :: GNU General Public License v3 (GPLv3)
Classifier: Natural Language :: English
Classifier: Programming Language :: Python :: 3
Classifier: Programming Language :: Python :: 3 :: Only
Classifier: Programming Language :: Python :: 3.7
Classifier: Programming Language :: Python :: 3.8
Classifier: Programming Language :: Python :: 3.9
Classifier: Programming Language :: Python :: 3.10
Requires-Python: >=3.7
Provides-Extra: dev
Provides-Extra: testing
License-File: LICENSE
